<?xml  version="1.0" encoding="UTF-8" ?>
<SW-Configuration>
	<MobileData>
	<PublicName>SM-T805</PublicName>
	</MobileData>
	<CustomerDataSet>
	<CSCName>T805OXA</CSCName>
	<CSCVersion>1CPH6</CSCVersion>
	<NbCustomer>5</NbCustomer>
	<CustomerData src="/Customer/BTU/customer.xml" />
	<CustomerData src="/Customer/DBT/customer.xml" />
	<CustomerData src="/Customer/ITV/customer.xml" />
	<CustomerData src="/Customer/XEO/customer.xml" />
	<CustomerData src="/Customer/XEF/customer.xml" />
	</CustomerDataSet>
</SW-Configuration>
